buildbot_pkg.py
buildbot_pkg-4.3.0.dist-info/METADATA
buildbot_pkg-4.3.0.dist-info/WHEEL
buildbot_pkg-4.3.0.dist-info/top_level.txt
buildbot_pkg-4.3.0.dist-info/RECORD
