Metadata-Version: 2.1
Name: buildbot-pkg
Version: 4.3.0
Summary: Buildbot packaging tools
Home-page: http://buildbot.net/
Author: Pierre Tardy
Author-email: tardyp@gmail.com
Classifier: License :: OSI Approved :: GNU General Public License v2 (GPLv2)
Requires-Dist: setuptools>=21.2.1
